bootils-0.1.0.dev4.dist-info/top_level.txt
bootils-0.1.0.dev4.dist-info/RECORD
bootils-0.1.0.dev4.dist-info/WHEEL
bootils-0.1.0.dev4.dist-info/metadata.json
bootils-0.1.0.dev4.dist-info/entry_points.txt
bootils-0.1.0.dev4.dist-info/DESCRIPTION.rst
bootils-0.1.0.dev4.dist-info/METADATA
bootils-0.1.0.dev4.data/data/EGG-INFO/LICENSE
bootils-0.1.0.dev4.data/data/EGG-INFO/README.md
bootils/_compat.py
bootils/__main__.py
bootils/__init__.py
