Metadata-Version: 2.0
Name: bootils
Version: 0.1.0.dev4
Summary: Bootils offers process boot-strapping utilities that support writing robust application/service launcher and process life-cycle management scripts.
Home-page: https://github.com/Build-The-Web/bootils
Author: Jürgen Hermann
Author-email: jh@web.de
License: Apache 2.0
Keywords: hosted.by.github,init.d,startup,launcher,monitoring,resilience,watchdog,log-scanner
Platform: UNKNOWN
Classifier: Development Status :: 2 - Pre-Alpha
Classifier: Environment :: Console
Classifier: Intended Audience :: Developers
Classifier: Intended Audience :: System Administrators
Classifier: License :: OSI Approved :: Apache Software License
Classifier: Operating System :: POSIX :: Linux
Classifier: Programming Language :: Python :: 2
Classifier: Programming Language :: Python :: 2.7
Classifier: Programming Language :: Python :: 3
Classifier: Programming Language :: Python :: 3.4
Classifier: Topic :: Software Development :: Libraries :: Python Modules
Classifier: Topic :: System :: Boot :: Init
Classifier: Topic :: System :: Monitoring
Classifier: Topic :: System :: Systems Administration
Classifier: Topic :: Utilities
Requires-Dist: click (>=3.3,<4)
Requires-Dist: colorama
Requires-Dist: pluginbase (>=0.3,<1)
Requires-Dist: psutil (==2.2.1)
